{"nodes": [{"id": "tech_node", "label": "tech-node.tsx", "file_type": "code", "source_file": "src\\components\\factory\\tech-node.tsx", "source_location": "L1"}, {"id": "tech_node_technode", "label": "TechNode()", "file_type": "code", "source_file": "src\\components\\factory\\tech-node.tsx", "source_location": "L23"}], "edges": [{"source": "tech_node", "target": "team", "relation": "imports_from", "confidence": "EXTRACTED", "source_file": "src\\components\\factory\\tech-node.tsx", "source_location": "L3", "weight": 1.0}, {"source": "tech_node", "target": "progress_bar", "relation": "imports_from", "confidence": "EXTRACTED", "source_file": "src\\components\\factory\\tech-node.tsx", "source_location": "L4", "weight": 1.0}, {"source": "tech_node", "target": "badge", "relation": "imports_from", "confidence": "EXTRACTED", "source_file": "src\\components\\factory\\tech-node.tsx", "source_location": "L5", "weight": 1.0}, {"source": "tech_node", "target": "button", "relation": "imports_from", "confidence": "EXTRACTED", "source_file": "src\\components\\factory\\tech-node.tsx", "source_location": "L6", "weight": 1.0}, {"source": "tech_node", "target": "tech_node_technode", "relation": "contains", "confidence": "EXTRACTED", "source_file": "src\\components\\factory\\tech-node.tsx", "source_location": "L23", "weight": 1.0}]}