{"nodes": [{"id": "car_performance_card", "label": "car-performance-card.tsx", "file_type": "code", "source_file": "src\\components\\factory\\car-performance-card.tsx", "source_location": "L1"}, {"id": "car_performance_card_pt", "label": "pt()", "file_type": "code", "source_file": "src\\components\\factory\\car-performance-card.tsx", "source_location": "L36"}, {"id": "car_performance_card_ringpath", "label": "ringPath()", "file_type": "code", "source_file": "src\\components\\factory\\car-performance-card.tsx", "source_location": "L41"}, {"id": "car_performance_card_sparkline", "label": "Sparkline()", "file_type": "code", "source_file": "src\\components\\factory\\car-performance-card.tsx", "source_location": "L140"}], "edges": [{"source": "car_performance_card", "target": "team", "relation": "imports_from", "confidence": "EXTRACTED", "source_file": "src\\components\\factory\\car-performance-card.tsx", "source_location": "L1", "weight": 1.0}, {"source": "car_performance_card", "target": "car_performance_card_pt", "relation": "contains", "confidence": "EXTRACTED", "source_file": "src\\components\\factory\\car-performance-card.tsx", "source_location": "L36", "weight": 1.0}, {"source": "car_performance_card", "target": "car_performance_card_ringpath", "relation": "contains", "confidence": "EXTRACTED", "source_file": "src\\components\\factory\\car-performance-card.tsx", "source_location": "L41", "weight": 1.0}, {"source": "car_performance_card", "target": "car_performance_card_sparkline", "relation": "contains", "confidence": "EXTRACTED", "source_file": "src\\components\\factory\\car-performance-card.tsx", "source_location": "L140", "weight": 1.0}]}