{"nodes": [{"id": "factory_insights", "label": "factory-insights.ts", "file_type": "code", "source_file": "src\\engine\\engineering\\factory-insights.ts", "source_location": "L1"}, {"id": "factory_insights_peeraveragedaxes", "label": "peerAveragedAxes()", "file_type": "code", "source_file": "src\\engine\\engineering\\factory-insights.ts", "source_location": "L24"}, {"id": "factory_insights_peerrank", "label": "peerRank()", "file_type": "code", "source_file": "src\\engine\\engineering\\factory-insights.ts", "source_location": "L36"}, {"id": "factory_insights_deltavsleaderseconds", "label": "deltaVsLeaderSeconds()", "file_type": "code", "source_file": "src\\engine\\engineering\\factory-insights.ts", "source_location": "L49"}, {"id": "factory_insights_fleethealth", "label": "fleetHealth()", "file_type": "code", "source_file": "src\\engine\\engineering\\factory-insights.ts", "source_location": "L65"}, {"id": "factory_insights_projectnextchange", "label": "projectNextChange()", "file_type": "code", "source_file": "src\\engine\\engineering\\factory-insights.ts", "source_location": "L77"}, {"id": "factory_insights_projectedgridloss", "label": "projectedGridLoss()", "file_type": "code", "source_file": "src\\engine\\engineering\\factory-insights.ts", "source_location": "L102"}, {"id": "factory_insights_atrcoefficientforposition", "label": "atrCoefficientForPosition()", "file_type": "code", "source_file": "src\\engine\\engineering\\factory-insights.ts", "source_location": "L111"}, {"id": "factory_insights_correlationdelta", "label": "correlationDelta()", "file_type": "code", "source_file": "src\\engine\\engineering\\factory-insights.ts", "source_location": "L126"}, {"id": "factory_insights_nextdeliveryround", "label": "nextDeliveryRound()", "file_type": "code", "source_file": "src\\engine\\engineering\\factory-insights.ts", "source_location": "L140"}, {"id": "factory_insights_windowresetsin", "label": "windowResetsIn()", "file_type": "code", "source_file": "src\\engine\\engineering\\factory-insights.ts", "source_location": "L162"}, {"id": "factory_insights_reliabilitymtbf", "label": "reliabilityMtbf()", "file_type": "code", "source_file": "src\\engine\\engineering\\factory-insights.ts", "source_location": "L174"}, {"id": "factory_insights_deterministicaerohistory", "label": "deterministicAeroHistory()", "file_type": "code", "source_file": "src\\engine\\engineering\\factory-insights.ts", "source_location": "L199"}], "edges": [{"source": "factory_insights", "target": "team", "relation": "imports_from", "confidence": "EXTRACTED", "source_file": "src\\engine\\engineering\\factory-insights.ts", "source_location": "L1", "weight": 1.0}, {"source": "factory_insights", "target": "car_performance", "relation": "imports_from", "confidence": "EXTRACTED", "source_file": "src\\engine\\engineering\\factory-insights.ts", "source_location": "L2", "weight": 1.0}, {"source": "factory_insights", "target": "component_lifecycle", "relation": "imports_from", "confidence": "EXTRACTED", "source_file": "src\\engine\\engineering\\factory-insights.ts", "source_location": "L3", "weight": 1.0}, {"source": "factory_insights", "target": "factory_insights_peeraveragedaxes", "relation": "contains", "confidence": "EXTRACTED", "source_file": "src\\engine\\engineering\\factory-insights.ts", "source_location": "L24", "weight": 1.0}, {"source": "factory_insights", "target": "factory_insights_peerrank", "relation": "contains", "confidence": "EXTRACTED", "source_file": "src\\engine\\engineering\\factory-insights.ts", "source_location": "L36", "weight": 1.0}, {"source": "factory_insights", "target": "factory_insights_deltavsleaderseconds", "relation": "contains", "confidence": "EXTRACTED", "source_file": "src\\engine\\engineering\\factory-insights.ts", "source_location": "L49", "weight": 1.0}, {"source": "factory_insights", "target": "factory_insights_fleethealth", "relation": "contains", "confidence": "EXTRACTED", "source_file": "src\\engine\\engineering\\factory-insights.ts", "source_location": "L65", "weight": 1.0}, {"source": "factory_insights", "target": "factory_insights_projectnextchange", "relation": "contains", "confidence": "EXTRACTED", "source_file": "src\\engine\\engineering\\factory-insights.ts", "source_location": "L77", "weight": 1.0}, {"source": "factory_insights", "target": "factory_insights_projectedgridloss", "relation": "contains", "confidence": "EXTRACTED", "source_file": "src\\engine\\engineering\\factory-insights.ts", "source_location": "L102", "weight": 1.0}, {"source": "factory_insights", "target": "factory_insights_atrcoefficientforposition", "relation": "contains", "confidence": "EXTRACTED", "source_file": "src\\engine\\engineering\\factory-insights.ts", "source_location": "L111", "weight": 1.0}, {"source": "factory_insights", "target": "factory_insights_correlationdelta", "relation": "contains", "confidence": "EXTRACTED", "source_file": "src\\engine\\engineering\\factory-insights.ts", "source_location": "L126", "weight": 1.0}, {"source": "factory_insights", "target": "factory_insights_nextdeliveryround", "relation": "contains", "confidence": "EXTRACTED", "source_file": "src\\engine\\engineering\\factory-insights.ts", "source_location": "L140", "weight": 1.0}, {"source": "factory_insights", "target": "factory_insights_windowresetsin", "relation": "contains", "confidence": "EXTRACTED", "source_file": "src\\engine\\engineering\\factory-insights.ts", "source_location": "L162", "weight": 1.0}, {"source": "factory_insights", "target": "factory_insights_reliabilitymtbf", "relation": "contains", "confidence": "EXTRACTED", "source_file": "src\\engine\\engineering\\factory-insights.ts", "source_location": "L174", "weight": 1.0}, {"source": "factory_insights", "target": "factory_insights_deterministicaerohistory", "relation": "contains", "confidence": "EXTRACTED", "source_file": "src\\engine\\engineering\\factory-insights.ts", "source_location": "L199", "weight": 1.0}]}